<!--This file autogenerated by the command
    configure Debug-U-32 --apply-default-debug-flags --trace2file disable --zlib no --xerces no --libcurl no --openssl no --lzma no 
-->

<Configuration>
    <ProjectPlatformSubdir>VisualStudio.Net-2015</ProjectPlatformSubdir>
    <CompilerDriver-C></CompilerDriver-C>
    <CompilerDriver-C++></CompilerDriver-C++>
    <ENABLE_ASSERTIONS>1</ENABLE_ASSERTIONS>
    <qFeatureFlag_LibCurl>no</qFeatureFlag_LibCurl>
    <qFeatureFlag_OpenSSL>no</qFeatureFlag_OpenSSL>
    <qFeatureFlag_WinHTTP>use-system</qFeatureFlag_WinHTTP>
    <qFeatureFlag_ATLMFC>use-system</qFeatureFlag_ATLMFC>
    <qFeatureFlag_Xerces>no</qFeatureFlag_Xerces>
    <qFeatureFlag_ZLib>no</qFeatureFlag_ZLib>
    <qFeatureFlag_LZMA>no</qFeatureFlag_LZMA>
    <EXTRA_COMPILER_ARGS></EXTRA_COMPILER_ARGS>
    <EXTRA_LINKER_ARGS> -rdynamic</EXTRA_LINKER_ARGS>
    <CrossCompiling>false</CrossCompiling>
    <ENABLE_TRACE2FILE>0</ENABLE_TRACE2FILE>
    <IncludeDebugSymbolsInLibraries>1</IncludeDebugSymbolsInLibraries>
    <IncludeDebugSymbolsInExecutables>1</IncludeDebugSymbolsInExecutables>
    <ExtraCDefines>
    </ExtraCDefines>
    <ExtraMakeDefines>
    </ExtraMakeDefines>
</Configuration>
